strawberry_resources/__init__.py
strawberry_resources/__main__.py
strawberry_resources/cli/__init__.py
strawberry_resources/cli/export.py
strawberry_resources/exporter.py
strawberry_resources/integrations/__init__.py
strawberry_resources/integrations/base.py
strawberry_resources/integrations/django.py
strawberry_resources/py.typed
strawberry_resources/queries.py
strawberry_resources/resolver.py
strawberry_resources/types.py
strawberry_resources/utils/__init__.py
strawberry_resources/utils/inspect.py
strawberry_resources/utils/pyutils.py
strawberry_resources-0.11.0.dist-info/LICENSE
strawberry_resources-0.11.0.dist-info/METADATA
strawberry_resources-0.11.0.dist-info/WHEEL
strawberry_resources-0.11.0.dist-info/entry_points.txt
strawberry_resources-0.11.0.dist-info/RECORD
