Metadata-Version: 2.1
Name: strawberry-resources
Version: 0.11.0
Summary: Introspection utilities to extract data from strawberry graphql
Home-page: https://github.com/blb-ventures/strawberry-resources
License: MIT
Keywords: strawberry,django,graphql,resources,forms
Author: Thiago Bellini Ribeiro
Author-email: thiago@bellini.dev
Requires-Python: >=3.8,<4.0
Classifier: Development Status :: 5 - Production/Stable
Classifier: Environment :: Web Environment
Classifier: Intended Audience :: Developers
Classifier: License :: OSI Approved :: MIT License
Classifier: Operating System :: OS Independent
Classifier: Programming Language :: Python
Classifier: Programming Language :: Python :: 3
Classifier: Programming Language :: Python :: 3.8
Classifier: Programming Language :: Python :: 3.9
Classifier: Programming Language :: Python :: 3.10
Classifier: Programming Language :: Python :: 3.11
Classifier: Programming Language :: Python :: 3.12
Provides-Extra: django
Requires-Dist: click (>=8.1.3)
Requires-Dist: django (>=3.2) ; extra == "django"
Requires-Dist: django-choices-field (>=2.0) ; extra == "django"
Requires-Dist: strawberry-graphql (>=0.236.0)
Requires-Dist: strawberry-graphql-django (>=0.47.0) ; extra == "django"
Requires-Dist: typing-extensions (>=4.2.0)
Project-URL: Documentation, https://github.com/blb-ventures/strawberry-resources
Project-URL: Repository, https://github.com/blb-ventures/strawberry-resources
